cobblestone/CsEngine.py
cobblestone/CsLogging.py
cobblestone/__init__.py
pkg/CsEngine.py
pkg/CsLogging.py
pkg/__init__.py
cobblestone-0.2.dist-info/LICENSE
cobblestone-0.2.dist-info/METADATA
cobblestone-0.2.dist-info/WHEEL
cobblestone-0.2.dist-info/top_level.txt
cobblestone-0.2.dist-info/RECORD
