Metadata-Version: 2.1
Name: cobblestone
Version: 0.2
Summary: Cobblestone: Basic game engine
Home-page: UNKNOWN
Author: Marco Meyer
Author-email: marco.meyerconde@gmail.com
License: MIT
Platform: UNKNOWN
